
<?xml version="1.0" encoding="UTF-8"?>
<theme>
   <formatVersion>7</formatVersion>

<view name="menu, system, basic, detailed, video, grid">  

		<image name="video_black" extra="true">
		
			<path>${framePath}deco_marvel.jpg</path>
			
		</image>
		
</view>

<view name="system">  

	  <text name="systemInfo">
        <pos>0 0.655</pos>
		<fontPath>${policePath}marvel.otf</fontPath>
	    <fontSize>0.035</fontSize>
        <zIndex>26</zIndex>
		<color>ffe336</color>
		<glowColor>ed000020</glowColor>
		<glowSize>3</glowSize>
      </text> 
	  
</view>

</theme>
